{
  "a": {
    "starter": true,
    "type": "monster",
    "value": [
      "troll",
      "turtle"
    ],
    "rewards": {
      "hp": 2,
      "cards": [
        "punch",
        "charge"
      ]
    }
  },
  "b": {
    "type": "monster",
    "value": [
      "turtle"
    ],
    "rewards": {
      "hp": 2,
      "cards": [
        "punch",
        "charge"
      ]
    }
  },
  "c": {
    "type": "monster",
    "value": [
      "troll"
    ]
  },
  "d": {
    "type": "monster",
    "value": [
      "boss"
    ]
  },
  "e": {
    "type": "monster",
    "value": [
      "troll"
    ]
  },
  "f": {
    "starter": true,
    "type": "tavern"
  },
  "g": {
    "type": "tavern"
  }
}